tenhoulog/__init__.py
tenhoulog/io.py
tenhoulog/models.py
tenhoulog/utils.py
tenhoulog-0.1.1.dist-info/WHEEL
tenhoulog-0.1.1.dist-info/METADATA
tenhoulog-0.1.1.dist-info/RECORD
